CHANGELOG.txt
LICENCE.TXT
MANIFEST.in
README.txt
setup.py
mageshbasiccalculator/__init__.py
mageshbasiccalculator.egg-info/PKG-INFO
mageshbasiccalculator.egg-info/SOURCES.txt
mageshbasiccalculator.egg-info/dependency_links.txt
mageshbasiccalculator.egg-info/top_level.txt
mageshbasiccalculator/basic/__init__.py
mageshbasiccalculator/basic/calculator.py
mageshbasiccalculator/scientific/__init__.py
mageshbasiccalculator/scientific/scientific_calculator.py
mageshbasiccalculator/test/test_calculator.py