Metadata-Version: 2.1
Name: mageshbasiccalculator
Version: 0.0.2
Summary: A very basic calculator
Home-page: 
Author: Mageshwari.MP
Author-email: 20i133@kce.ac.in
License: MIT
Keywords: calculator
Classifier: Development Status :: 5 - Production/Stable
Classifier: Intended Audience :: Education
Classifier: Operating System :: Microsoft :: Windows :: Windows 10
Classifier: License :: OSI Approved :: MIT License
Classifier: Programming Language :: Python :: 3
License-File: LICENCE.TXT
